<?xml version="1.0" ?>
<annotation>
   <folder>n000001</folder>
   <filename>0422_05.jpg</filename>
   <path>n000001/0422_05.jpg</path>
   <source>
      <database>Unknown</database>
   </source>
   <size>
      <width>195</width>
      <height>218</height>
   </size>
   <segmented>0</segmented>
   <object>
      <name>N000001</name>
      <pose>Unspecified</pose>
      <truncated>0</truncated>
      <difficult>0</difficult>
      <bndbox>
         <xmin>57</xmin>
         <ymin>53</ymin>
         <xmax>141</xmax>
         <ymax>163</ymax>
      </bndbox>
   </object>
</annotation>
